{
  "db_name": "PostgreSQL",
  "query": "\n                select * from lessons\n                where start between $1 and $2\n            ",
  "describe": {
    "columns": [
      {
        "ordinal": 0,
        "name": "id",
        "type_info": "Int4"
      },
      {
        "ordinal": 1,
        "name": "subject",
        "type_info": "Varchar"
      },
      {
        "ordinal": 2,
        "name": "teachers",
        "type_info": "Text"
      },
      {
        "ordinal": 3,
        "name": "location",
        "type_info": "Varchar"
      },
      {
        "ordinal": 4,
        "name": "start",
        "type_info": "Timestamptz"
      },
      {
        "ordinal": 5,
        "name": "end",
        "type_info": "Timestamptz"
      }
    ],
    "parameters": {
      "Left": [
        "Timestamptz",
        "Timestamptz"
      ]
    },
    "nullable": [
      false,
      false,
      false,
      false,
      false,
      false
    ]
  },
  "hash": "5cfa03bb742ebcef8fd8650d044c1f649b9660aad9de8de3a1004c13c129295b"
}
